{
  "name": "E-Ink Display - Publish Notes",
  "nodes": [
    {
      "parameters": {},
      "id": "manual-trigger-notes",
      "name": "When clicking 'Execute Workflow'",
      "type": "n8n-nodes-base.manualTrigger",
      "typeVersion": 1,
      "position": [100, 240]
    },
    {
      "parameters": {
        "jsCode": "return [\n  {\n    \"notes\": [\n      \"सब्जियां और फल बाजार से खरीदना न भूलें (Groceries)\",\n      \"Water backyard plants at 6:00 PM\",\n      \"Sanskrit learning session at 7:00 AM tomorrow\"\n    ]\n  }\n];"
      },
      "id": "code-notes-data",
      "name": "Format Notes Array",
      "type": "n8n-nodes-base.code",
      "typeVersion": 2,
      "position": [320, 240]
    },
    {
      "parameters": {
        "broker": "tcp://100.101.102.4:1883",
        "topic": "home/eink/notes",
        "message": "={{ JSON.stringify($json.notes) }}",
        "options": {
          "qos": 1,
          "retain": true
        }
      },
      "id": "mqtt-publish-notes",
      "name": "MQTT Publish Notes",
      "type": "n8n-nodes-base.mqtt",
      "typeVersion": 1,
      "position": [540, 240]
    }
  ],
  "connections": {
    "When clicking 'Execute Workflow'": {
      "main": [
        [
          {
            "node": "Format Notes Array",
            "type": "main",
            "index": 0
          }
        ]
      ]
    },
    "Format Notes Array": {
      "main": [
        [
          {
            "node": "MQTT Publish Notes",
            "type": "main",
            "index": 0
          }
        ]
      ]
    }
  },
  "active": false,
  "settings": {},
  "meta": {
    "templateCredsSetupCompleted": true
  }
}
